ashitakhurana_101703115_missing_val/__init__.py
ashitakhurana_101703115_missing_val/missing_val.py
ashitakhurana_101703115_missing-0.0.2.dist-info/LICENSE.txt
ashitakhurana_101703115_missing-0.0.2.dist-info/METADATA
ashitakhurana_101703115_missing-0.0.2.dist-info/WHEEL
ashitakhurana_101703115_missing-0.0.2.dist-info/top_level.txt
ashitakhurana_101703115_missing-0.0.2.dist-info/RECORD
